nanoget/__init__.py
nanoget/extraction_functions.py
nanoget/nanoget.py
nanoget/utils.py
nanoget/version.py
nanoget-1.19.4.data/data/LICENSE
nanoget-1.19.4.dist-info/licenses/LICENSE
scripts/create_feather.py
scripts/test.py
nanoget-1.19.4.dist-info/METADATA
nanoget-1.19.4.dist-info/WHEEL
nanoget-1.19.4.dist-info/top_level.txt
nanoget-1.19.4.dist-info/RECORD
