Metadata-Version: 2.4
Name: nanoget
Version: 1.19.4
Summary: Functions to extract information from Oxford Nanopore sequencing data and alignments.
Home-page: https://github.com/wdecoster/nanoget
Author: Wouter De Coster
Author-email: decosterwouter@gmail.com
License: GPLv3
Keywords: nanopore sequencing plotting quality control
Classifier: Development Status :: 4 - Beta
Classifier: Intended Audience :: Science/Research
Classifier: Topic :: Scientific/Engineering :: Bio-Informatics
Classifier: License :: OSI Approved :: GNU General Public License v3 (GPLv3)
Classifier: Programming Language :: Python :: 3
Classifier: Programming Language :: Python :: 3.3
Classifier: Programming Language :: Python :: 3.4
Classifier: Programming Language :: Python :: 3.5
Requires-Python: >=3
License-File: LICENSE
Requires-Dist: pandas>=2.0.0
Requires-Dist: numpy
Requires-Dist: biopython
Requires-Dist: pysam>0.10.0.0
Dynamic: author
Dynamic: author-email
Dynamic: classifier
Dynamic: description
Dynamic: description-content-type
Dynamic: home-page
Dynamic: keywords
Dynamic: license
Dynamic: license-file
Dynamic: requires-dist
Dynamic: requires-python
Dynamic: summary
